prodigy_teams/__init__.py
prodigy_teams/__main__.py
prodigy_teams/about.json
prodigy_teams/about.py
prodigy_teams/appdirs.py
prodigy_teams/auth.py
prodigy_teams/build.py
prodigy_teams/cli.py
prodigy_teams/config.py
prodigy_teams/errors.py
prodigy_teams/main.py
prodigy_teams/messages.py
prodigy_teams/ptc.json
prodigy_teams/query.py
prodigy_teams/read_version.py
prodigy_teams/ty.py
prodigy_teams/ui.py
prodigy_teams/util.py
prodigy_teams/commands/__init__.py
prodigy_teams/commands/_recipe_subcommand.py
prodigy_teams/commands/_state.py
prodigy_teams/commands/actions.py
prodigy_teams/commands/assets.py
prodigy_teams/commands/clusters.py
prodigy_teams/commands/config.py
prodigy_teams/commands/datasets.py
prodigy_teams/commands/general.py
prodigy_teams/commands/import_export.py
prodigy_teams/commands/packages.py
prodigy_teams/commands/paths.py
prodigy_teams/commands/projects.py
prodigy_teams/commands/publish_code.py
prodigy_teams/commands/publish_data.py
prodigy_teams/commands/recipes.py
prodigy_teams/commands/secrets.py
prodigy_teams/commands/tasks.py
prodigy_teams/commands/team.py
prodigy_teams/commands/files/__init__.py
prodigy_teams/commands/files/cp.py
prodigy_teams/commands/files/ls.py
prodigy_teams/commands/files/rm.py
prodigy_teams/commands/files/rsync.py
prodigy_teams/commands/files/stats.py
prodigy_teams/prodigy_teams_broker_sdk/__init__.py
prodigy_teams/prodigy_teams_broker_sdk/errors.py
prodigy_teams/prodigy_teams_broker_sdk/models.py
prodigy_teams/prodigy_teams_broker_sdk/py.typed
prodigy_teams/prodigy_teams_broker_sdk/ty.py
prodigy_teams/prodigy_teams_broker_sdk/util.py
prodigy_teams/prodigy_teams_broker_sdk/client/__init__.py
prodigy_teams/prodigy_teams_broker_sdk/client/base.py
prodigy_teams/prodigy_teams_broker_sdk/client/check.py
prodigy_teams/prodigy_teams_broker_sdk/client/data.py
prodigy_teams/prodigy_teams_broker_sdk/client/envs.py
prodigy_teams/prodigy_teams_broker_sdk/client/events.py
prodigy_teams/prodigy_teams_broker_sdk/client/files.py
prodigy_teams-0.2.1.dist-info/LICENSE
prodigy_teams-0.2.1.dist-info/METADATA
prodigy_teams-0.2.1.dist-info/WHEEL
prodigy_teams-0.2.1.dist-info/entry_points.txt
prodigy_teams-0.2.1.dist-info/top_level.txt
prodigy_teams-0.2.1.dist-info/RECORD
