Metadata-Version: 2.1
Name: prodigy-teams
Version: 0.2.1
Summary: Prodigy Teams Command Line Interface
Home-page: https://prodi.gy
Author: ExplosionAI GmbH
Author-email: contact@explosion.ai
License: All rights reserved
License-File: LICENSE
Requires-Dist: email-validator
Requires-Dist: httpx
Requires-Dist: packaging
Requires-Dist: pkginfo >=1.7
Requires-Dist: pydantic[email] <2.0.0,>1.10
Requires-Dist: pyjwt
Requires-Dist: radicli >=0.0.25
Requires-Dist: srsly >=2.4
Requires-Dist: wasabi >=0.8.2
